MANIFEST.in
README.md
setup.cfg
setup.py
pixiedust_rosie/__init__.py
pixiedust_rosie/pixie_rosie_UI.py
pixiedust_rosie/test.py
pixiedust_rosie.egg-info/PKG-INFO
pixiedust_rosie.egg-info/SOURCES.txt
pixiedust_rosie.egg-info/dependency_links.txt
pixiedust_rosie.egg-info/not-zip-safe
pixiedust_rosie.egg-info/requires.txt
pixiedust_rosie.egg-info/top_level.txt
pixiedust_rosie/classify/__init__.py
pixiedust_rosie/classify/adapt23.py
pixiedust_rosie/classify/classify_data.py
pixiedust_rosie/classify/destructure.py
pixiedust_rosie/classify/rosie_matcher.py
pixiedust_rosie/templates/finish_screen.html
pixiedust_rosie/templates/help_panel.html
pixiedust_rosie/templates/modify_screen.html
pixiedust_rosie/templates/newColumns_panel.html
pixiedust_rosie/templates/pattern_panel.html
pixiedust_rosie/templates/schema_screen.html
pixiedust_rosie/templates/suggestion_screen.html
pixiedust_rosie/templates/transform_buttons.html
pixiedust_rosie/templates/transform_screen.html