Metadata-Version: 1.0
Name: pixiedust-rosie
Version: 0.4
Summary: Data Wrangling
Home-page: https://github.com/ibm-watson-data-lab/pixiedust_rosie
Author: Jamie Jennings, Terry Antony, David Taieb, Raj Singh
Author-email: jamie@rosie-lang.org,terryantony122@gmail.com,david_taieb@us.ibm.com
License: Apache 2.0
Platform: UNKNOWN
